[
  {"weight": 1, "rateJmd": 650},
  {"weight": 2, "rateJmd": 800},
  {"weight": 3, "rateJmd": 950},
  {"weight": 4, "rateJmd": 1100},
  {"weight": 5, "rateJmd": 1250},
  {"weight": 6, "rateJmd": 1400},
  {"weight": 7, "rateJmd": 1550},
  {"weight": 8, "rateJmd": 1700},
  {"weight": 9, "rateJmd": 1850},
  {"weight": 10, "rateJmd": 2000},
  {"weight": 11, "rateJmd": 2200},
  {"weight": 12, "rateJmd": 2400},
  {"weight": 13, "rateJmd": 2600},
  {"weight": 14, "rateJmd": 2800},
  {"weight": 15, "rateJmd": 3000},
  {"weight": 16, "rateJmd": 3200},
  {"weight": 17, "rateJmd": 3400},
  {"weight": 18, "rateJmd": 3600},
  {"weight": 19, "rateJmd": 3800},
  {"weight": 20, "rateJmd": 4000},
  {"weight": 21, "rateJmd": 7800},
  {"weight": 22, "rateJmd": 8100},
  {"weight": 23, "rateJmd": 8300},
  {"weight": 24, "rateJmd": 8560},
  {"weight": 25, "rateJmd": 8920},
  {"weight": 26, "rateJmd": 9320},
  {"weight": 27, "rateJmd": 9720},
  {"weight": 28, "rateJmd": 10300},
  {"weight": 29, "rateJmd": 10560},
  {"weight": 30, "rateJmd": 10860},
  {"weight": 31, "rateJmd": 11040},
  {"weight": 32, "rateJmd": 11200},
  {"weight": 33, "rateJmd": 11640},
  {"weight": 34, "rateJmd": 11940},
  {"weight": 35, "rateJmd": 12240},
  {"weight": 36, "rateJmd": 12600},
  {"weight": 37, "rateJmd": 12900},
  {"weight": 38, "rateJmd": 13200},
  {"weight": 39, "rateJmd": 13500},
  {"weight": 40, "rateJmd": 13800},
  {"weight": 41, "rateJmd": 14100},
  {"weight": 42, "rateJmd": 14360},
  {"weight": 43, "rateJmd": 14560},
  {"weight": 44, "rateJmd": 14860},
  {"weight": 45, "rateJmd": 15160},
  {"weight": 46, "rateJmd": 15720},
  {"weight": 47, "rateJmd": 16080},
  {"weight": 48, "rateJmd": 16340},
  {"weight": 49, "rateJmd": 16660},
  {"weight": 50, "rateJmd": 17020},
  {"weight": 51, "rateJmd": 17640},
  {"weight": 52, "rateJmd": 18030},
  {"weight": 53, "rateJmd": 18320},
  {"weight": 54, "rateJmd": 18610},
  {"weight": 55, "rateJmd": 18810},
  {"weight": 56, "rateJmd": 19790},
  {"weight": 57, "rateJmd": 19880},
  {"weight": 58, "rateJmd": 20170},
  {"weight": 59, "rateJmd": 20760},
  {"weight": 60, "rateJmd": 20950},
  {"weight": 61, "rateJmd": 21440},
  {"weight": 62, "rateJmd": 21830},
  {"weight": 63, "rateJmd": 22220},
  {"weight": 64, "rateJmd": 22610},
  {"weight": 65, "rateJmd": 23000},
  {"weight": 66, "rateJmd": 23390},
  {"weight": 67, "rateJmd": 23780},
  {"weight": 68, "rateJmd": 24170},
  {"weight": 69, "rateJmd": 24560},
  {"weight": 70, "rateJmd": 24950},
  {"weight": 71, "rateJmd": 25240},
  {"weight": 72, "rateJmd": 25730},
  {"weight": 73, "rateJmd": 25920},
  {"weight": 74, "rateJmd": 26710},
  {"weight": 75, "rateJmd": 26900},
  {"weight": 76, "rateJmd": 27190},
  {"weight": 77, "rateJmd": 27680},
  {"weight": 78, "rateJmd": 28070},
  {"weight": 79, "rateJmd": 28460},
  {"weight": 80, "rateJmd": 28850},
  {"weight": 81, "rateJmd": 29240},
  {"weight": 82, "rateJmd": 29630},
  {"weight": 83, "rateJmd": 30020},
  {"weight": 84, "rateJmd": 30410},
  {"weight": 85, "rateJmd": 30800},
  {"weight": 86, "rateJmd": 31190},
  {"weight": 87, "rateJmd": 31580},
  {"weight": 88, "rateJmd": 31970},
  {"weight": 89, "rateJmd": 32260},
  {"weight": 90, "rateJmd": 32750},
  {"weight": 91, "rateJmd": 33140},
  {"weight": 92, "rateJmd": 33530},
  {"weight": 93, "rateJmd": 33920},
  {"weight": 94, "rateJmd": 34210},
  {"weight": 95, "rateJmd": 34700},
  {"weight": 96, "rateJmd": 35090},
  {"weight": 97, "rateJmd": 35480},
  {"weight": 98, "rateJmd": 36140},
  {"weight": 99, "rateJmd": 36260},
  {"weight": 100, "rateJmd": 36470},
  {"weight": 101, "rateJmd": 37160},
  {"weight": 102, "rateJmd": 37620},
  {"weight": 103, "rateJmd": 37980},
  {"weight": 104, "rateJmd": 38460},
  {"weight": 105, "rateJmd": 38820},
  {"weight": 106, "rateJmd": 39180},
  {"weight": 107, "rateJmd": 39660},
  {"weight": 108, "rateJmd": 40020},
  {"weight": 109, "rateJmd": 40380},
  {"weight": 110, "rateJmd": 40640},
  {"weight": 111, "rateJmd": 41120},
  {"weight": 112, "rateJmd": 41480},
  {"weight": 113, "rateJmd": 41840},
  {"weight": 114, "rateJmd": 42320},
  {"weight": 115, "rateJmd": 42680},
  {"weight": 116, "rateJmd": 43040},
  {"weight": 117, "rateJmd": 43620},
  {"weight": 118, "rateJmd": 43980},
  {"weight": 119, "rateJmd": 44340},
  {"weight": 120, "rateJmd": 44820},
  {"weight": 121, "rateJmd": 45180},
  {"weight": 122, "rateJmd": 45540},
  {"weight": 123, "rateJmd": 45900},
  {"weight": 124, "rateJmd": 46380},
  {"weight": 125, "rateJmd": 46740},
  {"weight": 126, "rateJmd": 47100},
  {"weight": 127, "rateJmd": 47580},
  {"weight": 128, "rateJmd": 47940},
  {"weight": 129, "rateJmd": 48300},
  {"weight": 130, "rateJmd": 48780},
  {"weight": 131, "rateJmd": 49140},
  {"weight": 132, "rateJmd": 49500},
  {"weight": 133, "rateJmd": 49860},
  {"weight": 134, "rateJmd": 50340},
  {"weight": 135, "rateJmd": 50700},
  {"weight": 136, "rateJmd": 51060},
  {"weight": 137, "rateJmd": 51540},
  {"weight": 138, "rateJmd": 51900},
  {"weight": 139, "rateJmd": 52100},
  {"weight": 140, "rateJmd": 52740},
  {"weight": 141, "rateJmd": 53100},
  {"weight": 142, "rateJmd": 53460},
  {"weight": 143, "rateJmd": 53940},
  {"weight": 144, "rateJmd": 54300},
  {"weight": 145, "rateJmd": 54660},
  {"weight": 146, "rateJmd": 55020},
  {"weight": 147, "rateJmd": 55500},
  {"weight": 148, "rateJmd": 55860},
  {"weight": 149, "rateJmd": 56120},
  {"weight": 150, "rateJmd": 56340},
  {"weight": 151, "rateJmd": 57060},
  {"weight": 152, "rateJmd": 57420},
  {"weight": 153, "rateJmd": 57900},
  {"weight": 154, "rateJmd": 58160},
  {"weight": 155, "rateJmd": 58620},
  {"weight": 156, "rateJmd": 59100},
  {"weight": 157, "rateJmd": 59460},
  {"weight": 158, "rateJmd": 59820},
  {"weight": 159, "rateJmd": 60180},
  {"weight": 160, "rateJmd": 60660},
  {"weight": 161, "rateJmd": 61020},
  {"weight": 162, "rateJmd": 61380},
  {"weight": 163, "rateJmd": 61860},
  {"weight": 164, "rateJmd": 62120},
  {"weight": 165, "rateJmd": 62580},
  {"weight": 166, "rateJmd": 63060},
  {"weight": 167, "rateJmd": 63420},
  {"weight": 168, "rateJmd": 63780},
  {"weight": 169, "rateJmd": 64160},
  {"weight": 170, "rateJmd": 64620},
  {"weight": 171, "rateJmd": 64980},
  {"weight": 172, "rateJmd": 65340},
  {"weight": 173, "rateJmd": 65820},
  {"weight": 174, "rateJmd": 66180},
  {"weight": 175, "rateJmd": 66540},
  {"weight": 176, "rateJmd": 67020},
  {"weight": 177, "rateJmd": 67380},
  {"weight": 178, "rateJmd": 67740},
  {"weight": 179, "rateJmd": 68120},
  {"weight": 180, "rateJmd": 68580},
  {"weight": 181, "rateJmd": 68940},
  {"weight": 182, "rateJmd": 69300},
  {"weight": 183, "rateJmd": 69780},
  {"weight": 184, "rateJmd": 70140},
  {"weight": 185, "rateJmd": 70500},
  {"weight": 186, "rateJmd": 70980},
  {"weight": 187, "rateJmd": 71340},
  {"weight": 188, "rateJmd": 71700},
  {"weight": 189, "rateJmd": 71980},
  {"weight": 190, "rateJmd": 72540},
  {"weight": 191, "rateJmd": 72900},
  {"weight": 192, "rateJmd": 73380},
  {"weight": 193, "rateJmd": 73740},
  {"weight": 194, "rateJmd": 74100},
  {"weight": 195, "rateJmd": 74460},
  {"weight": 196, "rateJmd": 74940},
  {"weight": 197, "rateJmd": 75300},
  {"weight": 198, "rateJmd": 75660},
  {"weight": 199, "rateJmd": 76140},
  {"weight": 200, "rateJmd": 76500}
]
